[{"place_id": 231914157, "licence": "Data \u00a9 OpenStreetMap contributors, ODbL 1.0. http://osm.org/copyright", "osm_type": "node", "osm_id": 293673885, "lat": "11.6645348", "lon": "92.7390448", "class": "place", "type": "city", "place_rank": 16, "importance": 0.4951309265433832, "addresstype": "city", "name": "Port Blair", "display_name": "Port Blair, Port Blair Tehsil, South Andaman, Andaman and Nicobar Islands, 744101, India", "boundingbox": ["11.5045348", "11.8245348", "92.5790448", "92.8990448"], "geojson": {"type": "Point", "coordinates": [92.7390448, 11.6645348]}}]